ncd_anon/__init__.py
ncd_anon/anonimizer.py
ncd_anon/convert.py
ncd_anon/entry_point/__init__.py
ncd_anon/entry_point/ncd_anonimize.py
ncd_anon-0.1.0.dist-info/entry_points.txt
ncd_anon-0.1.0.dist-info/METADATA
ncd_anon-0.1.0.dist-info/WHEEL
ncd_anon-0.1.0.dist-info/RECORD
