Metadata-Version: 2.1
Name: ncd-anon
Version: 0.1.0
Summary: 
Author: Jaap Oosterbroek
Author-email: jaap@net-sky.co
Requires-Python: >=3.10.0,<3.12
Classifier: Programming Language :: Python :: 3
Classifier: Programming Language :: Python :: 3.10
Classifier: Programming Language :: Python :: 3.11
Requires-Dist: charset-normalizer (==3.4.0)
Requires-Dist: jsonlines (==4.0.0)
Requires-Dist: pdfplumber (==0.11.4)
Requires-Dist: python-dotenv (>=1.0.1,<2.0.0)
Requires-Dist: torch (==2.5.1)
Requires-Dist: transformers (==4.47.0)
